pkce/__init__.py
pkce/py.typed
pkce-1.0.3.dist-info/LICENSE
pkce-1.0.3.dist-info/METADATA
pkce-1.0.3.dist-info/WHEEL
pkce-1.0.3.dist-info/top_level.txt
pkce-1.0.3.dist-info/RECORD
