Metadata-Version: 2.1
Name: pkce
Version: 1.0.3
Summary: PKCE Pyhton generator.
Home-page: https://github.com/RomeoDespres/pkce
Author: Roméo Després
Author-email: despres.romeo@gmail.com
License: MIT
Platform: UNKNOWN
Classifier: Programming Language :: Python :: 3
Classifier: License :: OSI Approved :: MIT License
Classifier: Operating System :: OS Independent
Classifier: Typing :: Typed
Requires-Python: >=3
